Workbook

Sheet fornecedores
A1: Período | B1: Fornecedor | C1: Último pagto ano | D1: CPF/CNPJ | E1: Valor Pago | F1: MÊS
A2: 2026 | B2: A. C. R. AVALIACOES LTDA - ME | C2: 46083 | D2: 08.890.317/0001-52 | E2: 3920 | F2: =TEXT(MONTH(Tabela2[[#This Row],[Último pagto ano]])*29,"mmmm") -> março
A3: 2026 | B3: ABBOTT LABORATORIOS DO BRASIL LTDA | C3: 46080 | D3: 56.998.701/0033-01 | E3: 266800 | F3: =TEXT(MONTH(Tabela2[[#This Row],[Último pagto ano]])*29,"mmmm") -> fevereiro
A4: 2026 | B4: ABC TRANSPORTES COLETIVOS VALE PARAIBA LTDA | C4: 46076 | D4: 45.176.864/0001-05 | E4: 1118.6 | F4: =TEXT(MONTH(Tabela2[[#This Row],[Último pagto ano]])*29,"mmmm") -> fevereiro
A5: 2026 | B5: ABIGAIR ANDRADE DO CARMO | C5: 46059 | D5: 515.520.518-20 | E5: 22 | F5: =TEXT(MONTH(Tabela2[[#This Row],[Último pagto ano]])*29,"mmmm") -> fevereiro
A6: 2026 | B6: ABR ACESSORIOS LTDA. | C6: 46045 | D6: 52.301.374/0001-40 | E6: 17990 | F6: =TEXT(MONTH(Tabela2[[#This Row],[Último pagto ano]])*29,"mmmm") -> janeiro
A7: 2026 | B7: ABRAAO MARTINS ROMERO | C7: 46048 | D7: 535.999.128-31 | E7: 44 | F7: =TEXT(MONTH(Tabela2[[#This Row],[Último pagto ano]])*29,"mmmm") -> janeiro
A8: 2026 | B8: ACACIA COMERCIO DE MEDICAMENTOS LTDA | C8: 46086 | D8: 03.945.035/0001-91 | E8: 60150.79 | F8: =TEXT(MONTH(Tabela2[[#This Row],[Último pagto ano]])*29,"mmmm") -> março
A9: 2026 | B9: ACACIO ALEXANDRE DOS SANTOS | C9: 46045 | D9: 371.601.778-78 | E9: 3000 | F9: =TEXT(MONTH(Tabela2[[#This Row],[Último pagto ano]])*29,"mmmm") -> janeiro
A10: 2026 | B10: ACAF- ASSOC. DOS CLUBES AMADORES DE FUT. SJC | C10: 46086 | D10: 04.533.920/0001-26 | E10: 109859.91 | F10: =TEXT(MONTH(Tabela2[[#This Row],[Último pagto ano]])*29,"mmmm") -> março
A11: 2026 | B11: ACAPU COMERCIO DE MADEIRAS LTDA | C11: 46028 | D11: 14.139.819/0001-49 | E11: 58082.77 | F11: =TEXT(MONTH(Tabela2[[#This Row],[Último pagto ano]])*29,"mmmm") -> janeiro
A12: 2026 | B12: ACQUA BRILHO LAVANDERIA LTDA | C12: 46076 | D12: 36.774.430/0001-08 | E12: 524 | F12: =TEXT(MONTH(Tabela2[[#This Row],[Último pagto ano]])*29,"mmmm") -> fevereiro
A13: 2026 | B13: ACTA MEDICINA DIAGNOSTICA LTDA | C13: 46072 | D13: 04.109.493/0001-53 | E13: 516623.5 | F13: =TEXT(MONTH(Tabela2[[#This Row],[Último pagto ano]])*29,"mmmm") -> fevereiro
... A4591: 2026 | B4591: 62.213.408 CARLOS EDUARDO RIBEIRO DOS SANTOS | C4591: 46042 | D4591: 62.213.408/0001-07 | E4591: 5600 | F4591: =TEXT(MONTH(Tabela2[[#This Row],[Último pagto ano]])*29,"mmmm") -> janeiro

Sheet analise
A1: MÊS | B1: TOTAL ÚLTIMO PAGAMENTO | C1: TOTAL DE ITENS
A2: janeiro | B2: =SUMIF(fornecedores!F:F,analise!A:A,fornecedores!E:E) -> 8500790 | C2: 926
A3: fevereiro | B3: =SUMIF(fornecedores!F:F,analise!A:A,fornecedores!E:E) -> 1.7460159e+08 | C3: 2632
A4: março | B4: =SUMIF(fornecedores!F:F,analise!A:A,fornecedores!E:E) -> 435880953 | C4: 1032
A5: abril | B5: =SUMIF(Tabela2[[#All],[Valor Pago]],#NOME?[[#This Row],['#REF!]],Tabela2[MÊS]) -> #NAME? | C5: =COUNTIF(fornecedores!E:E,analise!A:A) -> 0
A6: maio | B6: =SUMIF(Tabela2[[#All],[Valor Pago]],#NOME?[[#This Row],['#REF!]],Tabela2[MÊS]) -> #NAME? | C6: =COUNTIF(fornecedores!E:E,analise!A:A) -> 0
A7: junho | B7: =SUMIF(Tabela2[[#All],[Valor Pago]],#NOME?[[#This Row],['#REF!]],Tabela2[MÊS]) -> #NAME? | C7: =COUNTIF(fornecedores!E:E,analise!A:A) -> 0
A8: julho | B8: =SUMIF(Tabela2[[#All],[Valor Pago]],#NOME?[[#This Row],['#REF!]],Tabela2[MÊS]) -> #NAME? | C8: =COUNTIF(fornecedores!E:E,analise!A:A) -> 0
A9: agosto | B9: =SUMIF(Tabela2[[#All],[Valor Pago]],#NOME?[[#This Row],['#REF!]],Tabela2[MÊS]) -> #NAME? | C9: =COUNTIF(fornecedores!E:E,analise!A:A) -> 0
A10: setembro | B10: =SUMIF(Tabela2[[#All],[Valor Pago]],#NOME?[[#This Row],['#REF!]],Tabela2[MÊS]) -> #NAME? | C10: =COUNTIF(fornecedores!E:E,analise!A:A) -> 0
A11: outubro | B11: =SUMIF(Tabela2[[#All],[Valor Pago]],#NOME?[[#This Row],['#REF!]],Tabela2[MÊS]) -> #NAME? | C11: =COUNTIF(fornecedores!E:E,analise!A:A) -> 0
A12: novembro | B12: =SUMIF(Tabela2[[#All],[Valor Pago]],#NOME?[[#This Row],['#REF!]],Tabela2[MÊS]) -> #NAME? | C12: =COUNTIF(fornecedores!E:E,analise!A:A) -> 0
A13: dezembro | B13: =SUMIF(Tabela2[[#All],[Valor Pago]],#NOME?[[#This Row],['#REF!]],Tabela2[MÊS]) -> #NAME? | C13: =COUNTIF(fornecedores!E:E,analise!A:A) -> 0
